github_macros/__init__.py
github_macros/cli/__init__.py
github_macros/cli/_base.py
github_macros/cli/branch_protection.py
github_macros/cli/refresh.py
github_macros/cli/releases.py
github_macros/cli/repo_permissions.py
github_macros/common.py
github_macros/http.py
github_macros/models/__init__.py
github_macros/models/github.py
github_macros-2.0.0.dist-info/entry_points.txt
github_macros-2.0.0.dist-info/WHEEL
github_macros-2.0.0.dist-info/METADATA
github_macros-2.0.0.dist-info/RECORD
